setup.cfg
setup.py
MK_rada_package.egg-info/PKG-INFO
MK_rada_package.egg-info/SOURCES.txt
MK_rada_package.egg-info/dependency_links.txt
MK_rada_package.egg-info/entry_points.txt
MK_rada_package.egg-info/not-zip-safe
MK_rada_package.egg-info/top_level.txt
mk_rada_package/__init__.py
mk_rada_package/descriptors.py
mk_rada_package/rada_consoles.py
mk_rada_package/rada_databases.py
mk_rada_package/rada_factories.py
mk_rada_package/rada_metaclass.py
mk_rada_package/rada_models.py
mk_rada_package/verh_rada.py