Metadata-Version: 1.0
Name: MK-rada-package
Version: 0.1.dev0
Summary: rada_test
Home-page: UNKNOWN
Author: Mykola Kantsir
Author-email: UNKNOWN
License: UNKNOWN
Platform: UNKNOWN
